wzx_utils/__init__.py
wzx_utils-0.0.3.dist-info/METADATA
wzx_utils-0.0.3.dist-info/WHEEL
wzx_utils-0.0.3.dist-info/top_level.txt
wzx_utils-0.0.3.dist-info/RECORD
