Metadata-Version: 2.4
Name: wzx_utils
Version: 0.0.3
Summary: tool library
Author-email: vincent <zixun.wu98@outlook.com>
License: MIT
Classifier: Programming Language :: Python :: 3
Classifier: License :: OSI Approved :: MIT License
Requires-Python: >=3.10
